{
  "slug": "momentum-edge-runner",
  "name": "Momentum Edge V1",
  "description": "Ported from polymarket-test momentumBacktest.js (read-only source)",
  "version": 1,
  "source_code": "const DEFAULT_PARAMS = {\n  walletSize: 100,\n  maxOrderValue: 5,\n  minShares: 1,\n  entryWindowStart: 297,\n  entryWindowEnd: 0,\n  warmupSec: 3,\n  minAsk: 0.31,\n  maxAsk: 0.85,\n  minEdge: 0.03,\n  maxSpread: 0.05,\n  minDirectionalProb: 0.51,\n  minProbHighAsk: 0.51,\n  minDistanceAbs: 13,\n  inversionDistanceAbs: 15,\n  askSemEdge: 0.65,\n  entrySlippageMax: 0.02,\n  minLiquidityRatio: 1,\n  minSigma: 30,\r\n  sigmaMultiplier: 1,\r\n  distanceWeight: 1.8,\r\n  momentumWeight: 1.2,\r\n  lagWeight: 0.9,\r\n  fastMomentumSec: 10,\r\n  slowMomentumSec: 30,\r\n  slowMomentumWeight: 0.4,\r\n  historyWindowSec: 120,\r\n  oddsSumTolerance: 0.20,\r\n  fallbackExitBid: 0.01,\n  inversionSharesMultiplier: 2,\n  deteriorationEnabled: true,\n  inversionEnabled: true,\n  deteriorationOddFactor: 0.45,\n  deteriorationProbFactor: 0.45,\n  deteriorationRequiresCross: true,\n  dynamicEdgeEnabled: true,\n  edgeTier1MaxAsk: 0.35,\n  edgeTier1Min: 0.06,\n  edgeTier2MaxAsk: 0.50,\n  edgeTier2Min: 0.03,\n  edgeTier3MaxAsk: 0.65,\n  edgeTier3Min: 0.01,\n  edgeTier4MaxAsk: 0.75,\n  edgeTier4Min: -0.03,\n  edgeTier5Min: -0.08,\n  positionSizingMode: 'bankroll',\n  minStake: 1,\n  bankrollThreshold: 100,\n  bankrollPct: 0.05,\n  reinforcementEnabled: true,\n  reinforcementDistanceFactor: 1.36,\n  reinforcementShares: 0,\n  reinforcementStakeMultiplier: 1,\n  postInversionStopLossEnabled: true,\n  postInversionStopLossFactor: 0.50,\n  postInversionReentryShares: 0,\n  postInversionReentryMultiplier: 2,\n  postInversionReentryStakeMultiplier: 4,\n  allowedPositionSide: 'BOTH',\n  entryShares: 0,\n  reversalShares: 0,\n  strategyName: 'MOMENTUM_EDGE_MODEL_V1',\n  strategyDisplayName: 'Momentum Edge Model V1',\n};\n\r\nfunction toFiniteNumber(value) {\n  if (value == null || value === '') return null;\n  const numberValue = Number(value);\n  return Number.isFinite(numberValue) ? numberValue : null;\n}\n\r\nfunction toBool(value, fallback = false) {\r\n  if (value == null) return fallback;\r\n  return value === true || value === 'true' || value === 1 || value === '1';\r\n}\r\n\r\nfunction clamp(value, min, max) {\r\n  return Math.min(max, Math.max(min, value));\r\n}\r\n\r\nfunction clamp01(value) {\r\n  return clamp(value, 0, 1);\r\n}\r\n\r\nfunction normalizePrice(value, fallback) {\r\n  const numberValue = toFiniteNumber(value);\r\n  if (numberValue == null) return fallback;\r\n  return clamp(numberValue, 0.001, 0.999);\r\n}\r\n\r\nfunction normalizeAllowedPositionSide(value) {\n  const side = String(value || 'BOTH').toUpperCase();\n  return ['BOTH', 'UP', 'DOWN'].includes(side) ? side : 'BOTH';\n}\n\nfunction normalizePositionSizingMode(value) {\n  const mode = String(value || 'fixed').toLowerCase();\n  return mode === 'bankroll' ? 'bankroll' : 'fixed';\n}\n\r\nfunction logistic(value) {\r\n  return 1 / (1 + Math.exp(-clamp(value, -20, 20)));\r\n}\r\n\r\nfunction mean(values) {\r\n  if (!values.length) return 0;\r\n  return values.reduce((sum, value) => sum + value, 0) / values.length;\r\n}\r\n\r\nfunction std(values) {\r\n  if (values.length < 2) return 0;\r\n  const avg = mean(values);\r\n  return Math.sqrt(mean(values.map((value) => (value - avg) ** 2)));\r\n}\r\n\r\nfunction formatPrice(value) {\r\n  return `$${Number(value || 0).toFixed(4)}`;\r\n}\r\n\r\nfunction formatQty(value) {\r\n  const numberValue = Number(value || 0);\r\n  return Number.isInteger(numberValue) ? String(numberValue) : numberValue.toFixed(4).replace(/0+$/, '').replace(/\\.$/, '');\r\n}\r\n\r\nfunction mergeMomentumParams(raw = {}) {\r\n  const params = { ...DEFAULT_PARAMS };\r\n  const numericKeys = [\r\n    'walletSize', 'maxOrderValue', 'minShares', 'entryWindowStart', 'entryWindowEnd',\r\n    'warmupSec', 'minAsk', 'maxAsk', 'minEdge', 'maxSpread', 'minDirectionalProb',\r\n    'minProbHighAsk', 'minDistanceAbs', 'inversionDistanceAbs', 'askSemEdge',\r\n    'entrySlippageMax', 'minLiquidityRatio', 'minSigma', 'sigmaMultiplier',\r\n    'distanceWeight', 'momentumWeight', 'lagWeight', 'fastMomentumSec',\r\n    'slowMomentumSec', 'slowMomentumWeight', 'historyWindowSec', 'oddsSumTolerance',\n    'fallbackExitBid', 'inversionSharesMultiplier', 'entryShares', 'reversalShares',\n    'deteriorationOddFactor', 'deteriorationProbFactor', 'edgeTier1MaxAsk',\n    'edgeTier1Min', 'edgeTier2MaxAsk', 'edgeTier2Min', 'edgeTier3MaxAsk',\n    'edgeTier3Min', 'edgeTier4MaxAsk', 'edgeTier4Min', 'edgeTier5Min',\n    'minStake', 'bankrollThreshold', 'bankrollPct', 'reinforcementDistanceFactor',\n    'reinforcementShares', 'reinforcementStakeMultiplier', 'postInversionStopLossFactor',\n    'postInversionReentryShares', 'postInversionReentryMultiplier',\n    'postInversionReentryStakeMultiplier',\n  ];\n\r\n  for (const key of numericKeys) {\r\n    if (raw[key] == null) continue;\r\n    const value = toFiniteNumber(raw[key]);\r\n    if (value != null) params[key] = value;\r\n  }\r\n\r\n  params.walletSize = Math.max(1, params.walletSize);\r\n  params.maxOrderValue = Math.max(0.01, params.maxOrderValue);\r\n  params.minShares = Math.max(0.000001, params.minShares);\r\n  params.entryWindowStart = clamp(params.entryWindowStart, 0, 300);\r\n  params.entryWindowEnd = clamp(params.entryWindowEnd, 0, 300);\r\n  if (params.entryWindowStart < params.entryWindowEnd) {\r\n    [params.entryWindowStart, params.entryWindowEnd] = [params.entryWindowEnd, params.entryWindowStart];\r\n  }\r\n  params.warmupSec = clamp(params.warmupSec, 0, 120);\r\n  params.minAsk = normalizePrice(params.minAsk, DEFAULT_PARAMS.minAsk);\r\n  params.maxAsk = normalizePrice(params.maxAsk, DEFAULT_PARAMS.maxAsk);\r\n  if (params.maxAsk < params.minAsk) [params.maxAsk, params.minAsk] = [params.minAsk, params.maxAsk];\r\n  params.minEdge = clamp(params.minEdge, -0.99, 0.99);\r\n  params.maxSpread = clamp(params.maxSpread, 0.001, 0.99);\r\n  params.minDirectionalProb = clamp(params.minDirectionalProb, 0.001, 0.999);\r\n  params.minProbHighAsk = clamp(params.minProbHighAsk, 0.001, 0.999);\r\n  params.minDistanceAbs = Math.max(0, params.minDistanceAbs);\r\n  params.inversionDistanceAbs = Math.max(0, params.inversionDistanceAbs);\r\n  params.askSemEdge = normalizePrice(params.askSemEdge, DEFAULT_PARAMS.askSemEdge);\r\n  params.entrySlippageMax = clamp(params.entrySlippageMax, 0, 0.99);\r\n  params.minLiquidityRatio = clamp(params.minLiquidityRatio, 0.01, 1);\r\n  params.minSigma = Math.max(0.01, params.minSigma);\r\n  params.sigmaMultiplier = clamp(params.sigmaMultiplier, 0.1, 5);\r\n  params.distanceWeight = clamp(params.distanceWeight, -10, 10);\r\n  params.momentumWeight = clamp(params.momentumWeight, -10, 10);\r\n  params.lagWeight = clamp(params.lagWeight, -10, 10);\r\n  params.fastMomentumSec = clamp(params.fastMomentumSec, 1, 180);\r\n  params.slowMomentumSec = clamp(params.slowMomentumSec, params.fastMomentumSec, 300);\r\n  params.slowMomentumWeight = clamp(params.slowMomentumWeight, -5, 5);\r\n  params.historyWindowSec = clamp(params.historyWindowSec, params.slowMomentumSec, 600);\r\n  params.oddsSumTolerance = clamp(params.oddsSumTolerance, 0, 0.99);\r\n  params.fallbackExitBid = normalizePrice(params.fallbackExitBid, DEFAULT_PARAMS.fallbackExitBid);\r\n  params.inversionSharesMultiplier = Math.max(0, params.inversionSharesMultiplier);\n  params.entryShares = Math.max(0, params.entryShares);\n  params.reversalShares = Math.max(0, params.reversalShares);\n  params.deteriorationOddFactor = clamp(params.deteriorationOddFactor, 0.01, 1);\n  params.deteriorationProbFactor = clamp(params.deteriorationProbFactor, 0.01, 1);\n  params.edgeTier1MaxAsk = normalizePrice(params.edgeTier1MaxAsk, DEFAULT_PARAMS.edgeTier1MaxAsk);\n  params.edgeTier2MaxAsk = normalizePrice(params.edgeTier2MaxAsk, DEFAULT_PARAMS.edgeTier2MaxAsk);\n  params.edgeTier3MaxAsk = normalizePrice(params.edgeTier3MaxAsk, DEFAULT_PARAMS.edgeTier3MaxAsk);\n  params.edgeTier4MaxAsk = normalizePrice(params.edgeTier4MaxAsk, DEFAULT_PARAMS.edgeTier4MaxAsk);\n  params.edgeTier1Min = clamp(params.edgeTier1Min, -0.99, 0.99);\n  params.edgeTier2Min = clamp(params.edgeTier2Min, -0.99, 0.99);\n  params.edgeTier3Min = clamp(params.edgeTier3Min, -0.99, 0.99);\n  params.edgeTier4Min = clamp(params.edgeTier4Min, -0.99, 0.99);\n  params.edgeTier5Min = clamp(params.edgeTier5Min, -0.99, 0.99);\n  params.minStake = Math.max(0.01, params.minStake);\n  params.bankrollThreshold = Math.max(0, params.bankrollThreshold);\n  params.bankrollPct = clamp(params.bankrollPct, 0.0001, 1);\n  params.reinforcementDistanceFactor = Math.max(1, params.reinforcementDistanceFactor);\n  params.reinforcementShares = Math.max(0, params.reinforcementShares);\n  params.reinforcementStakeMultiplier = Math.max(0, params.reinforcementStakeMultiplier);\n  params.postInversionStopLossFactor = clamp(params.postInversionStopLossFactor, 0.01, 1);\n  params.postInversionReentryShares = Math.max(0, params.postInversionReentryShares);\n  params.postInversionReentryMultiplier = Math.max(0, params.postInversionReentryMultiplier);\n  params.postInversionReentryStakeMultiplier = Math.max(0, params.postInversionReentryStakeMultiplier);\n  params.deteriorationEnabled = toBool(raw.deteriorationEnabled, params.deteriorationEnabled);\n  params.inversionEnabled = toBool(raw.inversionEnabled, params.inversionEnabled);\n  params.deteriorationRequiresCross = toBool(raw.deteriorationRequiresCross, params.deteriorationRequiresCross);\n  params.dynamicEdgeEnabled = toBool(raw.dynamicEdgeEnabled, params.dynamicEdgeEnabled);\n  params.reinforcementEnabled = toBool(raw.reinforcementEnabled, params.reinforcementEnabled);\n  params.postInversionStopLossEnabled = toBool(raw.postInversionStopLossEnabled, params.postInversionStopLossEnabled);\n  params.allowedPositionSide = normalizeAllowedPositionSide(raw.allowedPositionSide ?? params.allowedPositionSide);\n  params.positionSizingMode = normalizePositionSizingMode(raw.positionSizingMode ?? params.positionSizingMode);\n  params.strategyName = String(raw.strategyName || params.strategyName || DEFAULT_PARAMS.strategyName);\n  params.strategyDisplayName = String(raw.strategyDisplayName || params.strategyDisplayName || DEFAULT_PARAMS.strategyDisplayName);\n  return params;\n}\n\nfunction parseBookLevels(rawLevels) {\n  let levels = rawLevels;\r\n  if (typeof rawLevels === 'string') {\r\n    try {\r\n      levels = JSON.parse(rawLevels);\r\n    } catch {\r\n      levels = [];\r\n    }\r\n  }\r\n  if (!Array.isArray(levels)) return [];\r\n\r\n  return levels\r\n    .map((level) => ({ price: toFiniteNumber(level?.price), size: toFiniteNumber(level?.size) }))\r\n    .filter((level) => level.price != null && level.size != null && level.price > 0 && level.size > 0)\r\n    .map((level) => ({ ...level, key: String(level.price) }))\r\n    .sort((left, right) => left.price - right.price);\r\n}\r\n\r\nfunction withFallbackAsk(levels, fallbackBestAsk) {\n  if (levels.length) return levels;\n  return [];\n}\n\r\nfunction pruneConsumedByVisibleLevels(levels, consumedByPrice) {\r\n  const visiblePriceKeys = new Set(levels.map((level) => level.key));\r\n  for (const key of Array.from(consumedByPrice.keys())) {\r\n    if (!visiblePriceKeys.has(key)) consumedByPrice.delete(key);\r\n  }\r\n}\r\n\r\nfunction availableAskQty(rawAsks, maxPrice, fallbackBestAsk) {\n  const levels = withFallbackAsk(parseBookLevels(rawAsks), fallbackBestAsk);\n  return levels.reduce((sum, level) => sum + (level.price <= maxPrice ? level.size : 0), 0);\n}\n\nfunction bankrollStake(params, walletBalance, multiplier = 1) {\n  const balance = Math.max(0, toFiniteNumber(walletBalance) ?? params.walletSize);\n  const baseStake = balance < params.bankrollThreshold ? params.minStake : balance * params.bankrollPct;\n  return Math.max(params.minStake, baseStake * Math.max(0, multiplier));\n}\n\nfunction sharesForStake(stake, price, minStake) {\n  if (price == null || price <= 0) return 0;\n  let shares = Math.floor(stake / price);\n  shares = Math.max(1, shares);\n  while (shares * price < minStake) shares += 1;\n  return shares;\n}\n\nfunction minEdgeForAsk(params, ask) {\n  if (!params.dynamicEdgeEnabled) return params.minEdge;\n  if (ask < params.edgeTier1MaxAsk) return params.edgeTier1Min;\n  if (ask < params.edgeTier2MaxAsk) return params.edgeTier2Min;\n  if (ask < params.edgeTier3MaxAsk) return params.edgeTier3Min;\n  if (ask < params.edgeTier4MaxAsk) return params.edgeTier4Min;\n  return params.edgeTier5Min;\n}\n\r\nfunction consumeAsksFromTick(rawAsks, maxPrice, requestedQty, consumedByPrice, fallbackBestAsk) {\r\n  const levels = withFallbackAsk(parseBookLevels(rawAsks), fallbackBestAsk);\r\n  if (!levels.length || requestedQty <= 0) return [];\r\n  pruneConsumedByVisibleLevels(levels, consumedByPrice);\r\n\r\n  const fills = [];\r\n  let remainingQty = requestedQty;\r\n  for (const level of levels) {\r\n    if (remainingQty <= 0) break;\r\n    if (level.price > maxPrice) continue;\r\n\r\n    const reservedQty = Math.min(consumedByPrice.get(level.key) || 0, level.size);\r\n    if (reservedQty > 0) consumedByPrice.set(level.key, reservedQty);\r\n    else consumedByPrice.delete(level.key);\r\n\r\n    const availableQty = level.size - reservedQty;\r\n    if (availableQty <= 0) continue;\r\n\r\n    const fillQty = Math.min(availableQty, remainingQty);\r\n    consumedByPrice.set(level.key, reservedQty + fillQty);\r\n    fills.push({ price: level.price, qty: fillQty });\r\n    remainingQty -= fillQty;\r\n  }\r\n\r\n  return fills;\r\n}\r\n\r\nfunction sideFields(tick, side) {\r\n  if (side === 'UP') {\r\n    const fallbackPrice = toFiniteNumber(tick.up_price);\r\n    return {\r\n      ask: toFiniteNumber(tick.up_best_ask) ?? fallbackPrice,\r\n      bid: toFiniteNumber(tick.up_best_bid) ?? fallbackPrice,\r\n      rawAsks: tick.up_book_asks,\r\n      price: fallbackPrice,\r\n    };\r\n  }\r\n  const fallbackPrice = toFiniteNumber(tick.down_price);\r\n  return {\r\n    ask: toFiniteNumber(tick.down_best_ask) ?? fallbackPrice,\r\n    bid: toFiniteNumber(tick.down_best_bid) ?? fallbackPrice,\r\n    rawAsks: tick.down_book_asks,\r\n    price: fallbackPrice,\r\n  };\r\n}\r\n\r\nfunction eventKey(tickOrState) {\r\n  return `${tickOrState.event_start ?? tickOrState.eventStart}|${tickOrState.condition_id ?? tickOrState.eventId}`;\r\n}\r\n\r\nfunction secondsRemaining(state, tick) {\r\n  return Math.max(0, (state.eventEnd - new Date(tick.ts)) / 1000);\r\n}\r\n\r\nfunction eventElapsedSec(state, tick) {\r\n  return Math.max(0, (new Date(tick.ts) - new Date(state.eventStart)) / 1000);\r\n}\r\n\r\nfunction sampleAgo(samples, seconds) {\r\n  if (!samples.length) return null;\r\n  const latest = samples[samples.length - 1];\r\n  const targetMs = latest.timeMs - (seconds * 1000);\r\n  return samples.find((sample) => sample.timeMs >= targetMs) || samples[0];\r\n}\r\n\r\nfunction recentAbsReturnVol(samples) {\r\n  if (samples.length < 3) return 0;\r\n  const returns = [];\r\n  for (let index = 1; index < samples.length; index++) {\r\n    const prev = samples[index - 1].btc;\r\n    const curr = samples[index].btc;\r\n    if (prev == null || curr == null) continue;\r\n    returns.push(Math.abs(curr - prev));\r\n  }\r\n  return std(returns);\r\n}\r\n\r\nfunction movementPerSecond(samples, seconds) {\r\n  if (samples.length < 2) return 0;\r\n  const latest = samples[samples.length - 1];\r\n  const previous = sampleAgo(samples, seconds);\r\n  if (!previous || previous === latest || latest.btc == null || previous.btc == null) return 0;\r\n  const dt = (latest.timeMs - previous.timeMs) / 1000;\r\n  if (dt <= 0) return 0;\r\n  return (latest.btc - previous.btc) / dt;\r\n}\r\n\r\nfunction createEventState(tick) {\r\n  const eventStart = tick.event_start;\r\n  const eventEnd = new Date(new Date(tick.event_start).getTime() + 300000);\r\n  return {\r\n    eventId: tick.condition_id,\r\n    eventStart,\r\n    eventEnd,\r\n    priceToBeat: toFiniteNumber(tick.price_to_beat),\n    lastTick: tick,\r\n    samples: [],\r\n    position: null,\r\n    entryTime: null,\r\n    entryDistanceToPtb: null,\r\n    entryTimeRemaining: null,\r\n    entryDiagnostics: null,\r\n    entryAsk: null,\r\n    entryProbability: null,\r\n    consumedAsksBySide: { UP: new Map(), DOWN: new Map() },\r\n    realizedPnl: 0,\r\n    exits: [],\r\n    reversals: [],\n    orders: [],\n    inverted: false,\n    deteriorated: false,\n    deteriorationAlert: false,\n    reinforced: false,\n    originalSide: null,\n    inversionAsk: null,\n    inversionQty: null,\n    postInversionStopLoss: false,\n    lastCandidate: null,\n    lastModel: null,\n  };\n}\n\r\nfunction addSample(state, tick, params) {\r\n  const tickTime = new Date(tick.ts).getTime();\r\n  state.samples.push({\r\n    timeMs: tickTime,\r\n    ts: tick.ts,\r\n    btc: toFiniteNumber(tick.btc_price),\r\n  });\r\n\r\n  const maxAgeMs = params.historyWindowSec * 1000;\r\n  while (state.samples.length > 1 && tickTime - state.samples[0].timeMs > maxAgeMs) {\r\n    state.samples.shift();\r\n  }\r\n}\r\n\r\nfunction estimateProbability(state, tick, params) {\r\n  const samples = state.samples;\r\n  const latest = samples[samples.length - 1];\r\n  const btcPrice = toFiniteNumber(tick.btc_price);\r\n  const priceToBeat = toFiniteNumber(state.priceToBeat ?? tick.price_to_beat);\r\n  if (btcPrice == null || priceToBeat == null || !latest) {\r\n    return {\r\n      pUp: 0.5,\r\n      pDown: 0.5,\r\n      sigma: params.minSigma,\r\n      distanceZ: 0,\r\n      momentumZ: 0,\r\n      marketLag: 0,\r\n      fastMove: 0,\r\n      slowMove: 0,\r\n      edgeUp: null,\r\n      edgeDown: null,\r\n    };\r\n  }\r\n\r\n  const timeRemainingSec = secondsRemaining(state, tick);\r\n  const rawVol = recentAbsReturnVol(samples);\r\n  const sigma = Math.max(\r\n    params.minSigma,\r\n    rawVol * Math.sqrt(Math.max(1, timeRemainingSec)) * params.sigmaMultiplier,\r\n  );\r\n  const distance = btcPrice - priceToBeat;\r\n  const distanceZ = distance / sigma;\r\n  const fastMove = movementPerSecond(samples, params.fastMomentumSec);\r\n  const slowMove = movementPerSecond(samples, params.slowMomentumSec);\r\n  const momentumZ = (fastMove + (params.slowMomentumWeight * slowMove)) / sigma;\r\n  const zPre = (params.distanceWeight * distanceZ) + (params.momentumWeight * momentumZ);\r\n  const pUpPre = logistic(zPre);\r\n  const upAsk = sideFields(tick, 'UP').ask ?? 0.5;\r\n  const downAsk = sideFields(tick, 'DOWN').ask ?? 0.5;\r\n  const marketLag = btcPrice >= priceToBeat ? pUpPre - upAsk : (1 - pUpPre) - downAsk;\r\n  const pUp = clamp(logistic(zPre + (params.lagWeight * marketLag)), 0.001, 0.999);\r\n  const pDown = 1 - pUp;\r\n\r\n  return {\r\n    pUp,\r\n    pDown,\r\n    sigma,\r\n    distanceZ,\r\n    momentumZ,\r\n    marketLag,\r\n    fastMove,\r\n    slowMove,\r\n    edgeUp: upAsk != null ? pUp - upAsk : null,\r\n    edgeDown: downAsk != null ? pDown - downAsk : null,\r\n  };\r\n}\r\n\r\nfunction oddsAreValid(tick, params) {\r\n  const upAsk = sideFields(tick, 'UP').ask;\r\n  const downAsk = sideFields(tick, 'DOWN').ask;\r\n  if (upAsk == null || downAsk == null) return false;\r\n  const sum = upAsk + downAsk;\r\n  return sum >= 1 - params.oddsSumTolerance && sum <= 1 + params.oddsSumTolerance;\r\n}\r\n\r\nfunction evaluateCandidate({ side, fields, probability, distanceAbs, params, walletBalance }) {\n  const ask = fields.ask;\r\n  const bid = fields.bid;\r\n  if (ask == null) return { approved: false, reason: 'sem ask' };\r\n  if (ask < params.minAsk) return { approved: false, reason: `ask ${ask.toFixed(2)} < minAsk ${params.minAsk}` };\r\n  if (ask > params.maxAsk) return { approved: false, reason: `ask ${ask.toFixed(2)} > maxAsk ${params.maxAsk}` };\r\n\r\n  const minProbability = params.dynamicEdgeEnabled\n    ? params.minDirectionalProb\n    : (ask >= params.askSemEdge ? params.minProbHighAsk : params.minDirectionalProb);\n  if (probability < minProbability) {\n    return { approved: false, reason: `prob ${probability.toFixed(2)} < min ${minProbability}` };\n  }\n\n  const edge = probability - ask;\n  const requiredEdge = minEdgeForAsk(params, ask);\n  if ((params.dynamicEdgeEnabled || ask < params.askSemEdge) && edge < requiredEdge) {\n    return { approved: false, reason: `edge ${edge.toFixed(3)} < minEdge ${requiredEdge} (ask=${ask.toFixed(2)})` };\n  }\n\r\n  const spread = bid != null ? Math.max(0, ask - bid) : null;\r\n  if (spread != null && spread > params.maxSpread) {\r\n    return { approved: false, reason: `spread ${spread.toFixed(2)} > max ${params.maxSpread}` };\r\n  }\r\n\r\n  if (distanceAbs < params.minDistanceAbs) {\r\n    return { approved: false, reason: `dist $${distanceAbs.toFixed(0)} < min $${params.minDistanceAbs}` };\r\n  }\r\n\r\n  const maxFill = Math.min(params.maxAsk, ask + params.entrySlippageMax);\n  let quantity = 0;\n  if (params.positionSizingMode === 'bankroll') {\n    quantity = sharesForStake(bankrollStake(params, walletBalance), maxFill, params.minStake);\n  } else if (params.entryShares > 0) {\n    quantity = params.entryShares;\n    const estimatedCost = quantity * maxFill;\n    if (estimatedCost > params.maxOrderValue) {\n      return { approved: false, reason: `custo estimado $${estimatedCost.toFixed(2)} > maxOrderValue $${params.maxOrderValue}` };\r\n    }\r\n  } else {\r\n    quantity = Math.floor(params.maxOrderValue / Math.max(maxFill, 0.001));\r\n  }\r\n  if (quantity < params.minShares) return { approved: false, reason: 'quantidade calculada abaixo do mínimo' };\r\n\r\n  return {\r\n    approved: true,\r\n    reason: 'ok',\r\n    side,\r\n    fields,\r\n    ask,\r\n    bid,\r\n    probability,\r\n    edge,\r\n    spread,\r\n    maxFill,\r\n    quantity,\r\n  };\r\n}\r\n\r\nfunction scoreCandidate(state, tick, params, walletBalance) {\n  const btcPrice = toFiniteNumber(tick.btc_price);\r\n  const priceToBeat = toFiniteNumber(state.priceToBeat ?? tick.price_to_beat);\r\n  if (btcPrice == null || priceToBeat == null) return null;\r\n  if (!oddsAreValid(tick, params)) return null;\r\n\r\n  const distanceAbs = Math.abs(btcPrice - priceToBeat);\r\n  const model = estimateProbability(state, tick, params);\r\n  state.lastModel = model;\r\n\r\n  const alignedSide = btcPrice >= priceToBeat ? 'UP' : 'DOWN';\r\n  if (params.allowedPositionSide !== 'BOTH' && params.allowedPositionSide !== alignedSide) return null;\r\n\r\n  const fields = sideFields(tick, alignedSide);\r\n  const probability = alignedSide === 'UP' ? model.pUp : model.pDown;\r\n  const candidate = evaluateCandidate({ side: alignedSide, fields, probability, distanceAbs, params, walletBalance });\n  state.lastCandidate = {\r\n    side: alignedSide,\r\n    ask: fields.ask,\r\n    bid: fields.bid,\r\n    probability,\r\n    edge: fields.ask != null ? probability - fields.ask : null,\r\n    spread: fields.ask != null && fields.bid != null ? fields.ask - fields.bid : null,\r\n    distanceAbs,\r\n    model,\r\n    approved: candidate.approved,\r\n    reason: candidate.reason,\r\n  };\r\n\r\n  return candidate.approved ? candidate : null;\r\n}\r\n\r\nfunction createPosition(side, fills) {\r\n  const totalQty = fills.reduce((sum, fill) => sum + fill.qty, 0);\r\n  const totalCost = fills.reduce((sum, fill) => sum + (fill.qty * fill.price), 0);\r\n  return {\r\n    side,\r\n    totalQty,\r\n    remainingQty: totalQty,\r\n    totalCost,\r\n    openCost: totalCost,\r\n    avgEntryPrice: totalQty > 0 ? totalCost / totalQty : 0,\r\n    fills,\r\n  };\r\n}\r\n\r\nfunction computeAdvancedMetrics(events, params, totalPnl, totalEntries, totalWins, totalLosses) {\r\n  const enteredEvents = events.filter((item) => item.reason !== 'no_entry');\r\n  const pnls = enteredEvents.map((item) => Number(item.finalPnl || 0));\r\n  const wins = pnls.filter((value) => value > 0);\r\n  const losses = pnls.filter((value) => value < 0);\r\n  const grossProfit = wins.reduce((sum, value) => sum + value, 0);\r\n  const grossLoss = losses.reduce((sum, value) => sum + Math.abs(value), 0);\r\n  const avgWin = wins.length ? grossProfit / wins.length : 0;\r\n  const avgLoss = losses.length ? grossLoss / losses.length : 0;\r\n  const avgPnl = totalEntries > 0 ? totalPnl / totalEntries : 0;\r\n  const pnlStd = std(pnls);\r\n  const downsideStd = std(losses);\r\n  const winProbability = totalEntries > 0 ? totalWins / totalEntries : 0;\r\n  const lossProbability = totalEntries > 0 ? totalLosses / totalEntries : 0;\r\n  const payoff = avgLoss > 0 ? avgWin / avgLoss : (avgWin > 0 ? Number.POSITIVE_INFINITY : 0);\r\n  const edgePerTrade = (winProbability * avgWin) - (lossProbability * avgLoss);\r\n  const riskUnits = avgLoss > 0 ? Math.max(1, Math.floor(params.walletSize / avgLoss)) : 99;\r\n  const ruinBase = payoff > 0 && winProbability > 0 ? lossProbability / Math.max(0.000001, winProbability * payoff) : 1;\r\n\r\n  return {\r\n    grossProfit,\r\n    grossLoss,\r\n    profitFactor: grossLoss > 0 ? grossProfit / grossLoss : (grossProfit > 0 ? Number.POSITIVE_INFINITY : 0),\r\n    payoff,\r\n    expectancy: avgPnl,\r\n    sharpe: pnlStd > 0 ? avgPnl / pnlStd : 0,\r\n    sortino: downsideStd > 0 ? avgPnl / downsideStd : 0,\r\n    riskOfRuin: edgePerTrade > 0 ? clamp(Math.pow(clamp01(ruinBase), riskUnits), 0, 1) : 1,\r\n  };\r\n}\r\n\r\nfunction createBacktestRunner(rawParams = {}) {\r\n  const params = mergeMomentumParams(rawParams);\r\n  const log = [];\r\n  const events = [];\r\n  const equity = [];\r\n  const completedEvents = new Set();\r\n\r\n  let totalEvents = 0;\r\n  let totalEntries = 0;\r\n  let totalWins = 0;\r\n  let totalLosses = 0;\r\n  let totalNoEntry = 0;\r\n  let totalPnl = 0;\r\n  let ticksProcessed = 0;\r\n  let periodStart = null;\r\n  let periodEnd = null;\r\n  let current = null;\r\n\r\n  const addLog = (ts, msg, type = 'info') => {\r\n    log.push({ ts, msg, type });\r\n  };\r\n\r\n  const currentOpenAveragePrice = () => {\n    if (!current?.position || current.position.remainingQty <= 0) return 0;\n    return current.position.openCost / Math.max(0.000001, current.position.remainingQty);\n  };\n\n  const currentWalletBalance = () => params.walletSize + totalPnl + (current?.realizedPnl || 0);\n\r\n  const executeSell = (tick, qty, rawPrice, reason, type = 'stop') => {\r\n    if (!current?.position || current.position.remainingQty <= 0 || qty <= 0) return 0;\r\n    const price = rawPrice != null && rawPrice > 0 ? rawPrice : params.fallbackExitBid;\r\n    const sellQty = Math.min(qty, current.position.remainingQty);\r\n    const avgOpenCost = currentOpenAveragePrice();\r\n    const consumedCost = avgOpenCost * sellQty;\r\n    const proceeds = sellQty * price;\r\n    const pnl = proceeds - consumedCost;\r\n    current.position.remainingQty -= sellQty;\r\n    current.position.openCost = Math.max(0, current.position.openCost - consumedCost);\r\n    current.realizedPnl += pnl;\r\n    current.exits.push({ time: tick.ts, side: current.position.side, qty: sellQty, price, proceeds, pnl, reason });\r\n    addLog(tick.ts, `${reason.toUpperCase()} | ${current.position.side} ${formatQty(sellQty)} @ ${formatPrice(price)} | PnL ${pnl >= 0 ? '+' : ''}$${pnl.toFixed(2)}`, type);\n    return sellQty;\n  };\n\n  const executeBuy = (tick, side, requestedQty, maxFillPrice, source, model, distanceAbs, timeRemainingSec, consumedMap = null) => {\n    const fields = sideFields(tick, side);\n    if (fields.ask == null || fields.ask <= 0 || requestedQty <= 0) return null;\n\n    const consumed = consumedMap || current.consumedAsksBySide[side];\n    const availableQty = availableAskQty(fields.rawAsks, maxFillPrice, fields.ask);\n    if (availableQty < requestedQty * params.minLiquidityRatio) return null;\n\n    const fills = consumeAsksFromTick(fields.rawAsks, maxFillPrice, requestedQty, consumed, fields.ask);\n    const filledQty = fills.reduce((sum, fill) => sum + fill.qty, 0);\n    const cost = fills.reduce((sum, fill) => sum + (fill.qty * fill.price), 0);\n    if (filledQty < Math.max(params.minShares, requestedQty * params.minLiquidityRatio) || cost <= 0) return null;\n\n    const timedFills = fills.map((fill) => ({ ...fill, time: tick.ts }));\n    return {\n      side,\n      source,\n      requestedQty,\n      filledQty,\n      maxPrice: maxFillPrice,\n      avgPrice: cost / filledQty,\n      cost,\n      createdAt: tick.ts,\n      probability: side === 'UP' ? model.pUp : model.pDown,\n      distanceAbs,\n      timeRemainingSec,\n      fills: timedFills,\n    };\n  };\n\n  const addToPosition = (order) => {\n    if (!current?.position || !order || order.filledQty <= 0) return;\n    current.position.totalQty += order.filledQty;\n    current.position.remainingQty += order.filledQty;\n    current.position.totalCost += order.cost;\n    current.position.openCost += order.cost;\n    current.position.avgEntryPrice = current.position.totalCost / current.position.totalQty;\n    current.position.fills.push(...order.fills.map((fill) => ({ ...fill })));\n    current.orders.push({ ...order, fills: order.fills.map((fill) => ({ ...fill })) });\n  };\n\r\n  const pushNoEntryEvent = (closeTs) => {\r\n    totalNoEntry++;\r\n    events.push({\r\n      eventId: current.eventId,\r\n      eventStart: current.eventStart,\r\n      eventEnd: current.eventEnd.toISOString(),\r\n      positionType: null,\r\n      entryTime: null,\r\n      entryDistanceToPtb: null,\r\n      entryTimeRemaining: null,\r\n      quantity: 0,\r\n      cost: 0,\r\n      profitOrders: [],\r\n      exits: [],\r\n      reversals: [],\r\n      expirationResult: null,\r\n      winnerSide: null,\r\n      finalPnl: 0,\r\n      reason: 'no_entry',\r\n      closedAt: closeTs,\r\n      diagnostics: { lastCandidate: current.lastCandidate, lastModel: current.lastModel },\r\n    });\r\n    equity.push({ ts: closeTs, pnl: totalPnl });\r\n  };\r\n\r\n  const finalizeCurrentEvent = (reason, closeTs = null) => {\r\n    if (!current) return;\r\n    const key = eventKey(current);\r\n    completedEvents.add(key);\r\n    const tick = current.lastTick;\r\n    const ts = closeTs || current.eventEnd.toISOString();\r\n\r\n    if (!current.position) {\r\n      pushNoEntryEvent(ts);\r\n      current = null;\r\n      return;\r\n    }\r\n\r\n    let expiryPnl = 0;\r\n    let winnerSide = null;\r\n    let expirationResult = 'LOSS';\r\n\r\n    if (current.position.remainingQty > 0) {\r\n      const priceToBeat = toFiniteNumber(current.priceToBeat ?? tick.price_to_beat);\n      const btcPrice = toFiniteNumber(tick.btc_price);\n      winnerSide = btcPrice != null && priceToBeat != null && btcPrice >= priceToBeat ? 'UP' : 'DOWN';\n      const payout = current.position.side === winnerSide ? current.position.remainingQty : 0;\r\n      expiryPnl = payout - current.position.openCost;\r\n      current.position.remainingQty = 0;\r\n      current.position.openCost = 0;\r\n      current.realizedPnl += expiryPnl;\r\n      expirationResult = current.position.side === winnerSide && !current.inverted ? 'WIN' : 'LOSS';\r\n      addLog(ts, `EXPIRACAO | ${current.position.side} vs ${winnerSide} | PnL ${expiryPnl >= 0 ? '+' : ''}$${expiryPnl.toFixed(2)}`, expiryPnl >= 0 ? 'profit' : 'loss');\r\n    }\r\n\r\n    const finalPnl = current.realizedPnl;\r\n    totalPnl += finalPnl;\r\n    const isWin = !current.inverted && finalPnl > 0;\r\n    if (isWin) totalWins++;\r\n    else totalLosses++;\r\n\r\n    const finalReason = current.deteriorated ? 'deterioration_inversion' : current.inverted ? 'cross_inversion' : reason;\r\n    events.push({\r\n      eventId: current.eventId,\r\n      eventStart: current.eventStart,\r\n      eventEnd: current.eventEnd.toISOString(),\r\n      positionType: current.position.side,\r\n      entryTime: current.entryTime,\r\n      entryDistanceToPtb: current.entryDistanceToPtb,\r\n      entryTimeRemaining: current.entryTimeRemaining,\r\n      quantity: current.position.totalQty,\r\n      cost: current.position.totalCost,\r\n      avgEntryPrice: current.position.avgEntryPrice,\r\n      fills: current.position.fills.map((fill) => ({ ...fill })),\r\n      profitOrders: [],\r\n      exits: current.exits.map((exit) => ({ ...exit })),\r\n      reversals: current.reversals.map((reversal) => ({\r\n        ...reversal,\r\n        entryFills: reversal.entryFills.map((fill) => ({ ...fill })),\r\n      })),\r\n      expirationResult,\r\n      winnerSide,\r\n      expiryPnl,\r\n      finalPnl,\r\n      reason: finalReason,\r\n      closedAt: ts,\r\n      orders: current.orders.map((order) => ({ ...order, fills: order.fills.map((fill) => ({ ...fill })) })),\r\n      diagnostics: {\r\n        ...current.entryDiagnostics,\r\n        inverted: current.inverted,\n        deteriorated: current.deteriorated,\n        reinforced: current.reinforced,\n        postInversionStopLoss: current.postInversionStopLoss,\n      },\n    });\n\r\n    equity.push({ ts, pnl: totalPnl });\r\n    addLog(ts, `EVENTO FIN | Momentum ${current.position.side} | PnL ${finalPnl >= 0 ? '+' : ''}$${finalPnl.toFixed(2)} | carteira $${(params.walletSize + totalPnl).toFixed(2)}`, finalPnl >= 0 ? 'profit' : 'loss');\r\n    current = null;\r\n  };\r\n\r\n  const startEvent = (tick) => {\n    current = createEventState(tick);\n    totalEvents++;\n    addLog(tick.ts, `Evento: ${new Date(tick.event_start).toISOString().slice(11, 19)} | ${params.strategyDisplayName}`, 'info');\n  };\n\r\n  const tryReversePosition = (tick, toSide, reason, model, distanceAbs, timeRemainingSec) => {\r\n    if (!current?.position || current.position.remainingQty <= 0) return false;\r\n    if (params.reversalShares <= 0 && params.inversionSharesMultiplier <= 0) return false;\r\n\r\n    const reverseFields = sideFields(tick, toSide);\r\n    if (reverseFields.ask == null || reverseFields.ask <= 0) return false;\r\n\r\n    const fromSide = current.position.side;\r\n    const fromQty = current.position.remainingQty;\r\n    const fromOpenCost = current.position.openCost;\r\n    let targetQty = 0;\r\n    if (params.reversalShares > 0) {\n      targetQty = params.reversalShares;\n    } else {\n      targetQty = fromQty * params.inversionSharesMultiplier;\n    }\n\n    const maxFillPrice = Math.min(0.999, reverseFields.ask + params.entrySlippageMax);\n    if (params.positionSizingMode === 'bankroll') {\n      targetQty = Math.max(\n        targetQty,\n        sharesForStake(bankrollStake(params, currentWalletBalance(), params.inversionSharesMultiplier), maxFillPrice, params.minStake),\n      );\n    }\n    const availableQty = availableAskQty(reverseFields.rawAsks, maxFillPrice, reverseFields.ask);\n    if (availableQty < targetQty * params.minLiquidityRatio) return false;\r\n\r\n    const consumedClone = new Map(current.consumedAsksBySide[toSide]);\r\n    const fills = consumeAsksFromTick(\r\n      reverseFields.rawAsks,\r\n      maxFillPrice,\r\n      targetQty,\r\n      consumedClone,\r\n      reverseFields.ask,\r\n    );\r\n    const filledQty = fills.reduce((sum, fill) => sum + fill.qty, 0);\r\n    const entryCost = fills.reduce((sum, fill) => sum + (fill.qty * fill.price), 0);\r\n    if (filledQty < Math.max(params.minShares, targetQty * params.minLiquidityRatio) || entryCost <= 0) return false;\r\n\r\n    const exitFields = sideFields(tick, fromSide);\r\n    const exitPrice = exitFields.bid != null && exitFields.bid > 0 ? exitFields.bid : params.fallbackExitBid;\r\n    const soldQty = executeSell(tick, fromQty, exitPrice, reason, 'stop');\r\n    if (soldQty <= 0) return false;\r\n\r\n    const timedFills = fills.map((fill) => ({ ...fill, time: tick.ts }));\r\n    current.consumedAsksBySide[toSide] = consumedClone;\r\n    current.position = createPosition(toSide, timedFills);\n    current.inverted = true;\n    current.deteriorated = current.deteriorated || reason === 'deterioracao';\n    current.inversionAsk = reverseFields.ask;\n    current.inversionQty = filledQty;\n    current.reversals.push({\n      time: tick.ts,\r\n      reason,\r\n      fromSide,\r\n      toSide,\r\n      soldQty,\r\n      exitPrice,\r\n      exitProceeds: soldQty * exitPrice,\r\n      fromOpenCost,\r\n      adverseDistance: distanceAbs,\r\n      timeRemainingSec,\r\n      entryQty: filledQty,\r\n      entryCost,\r\n      avgEntryPrice: entryCost / filledQty,\r\n      probability: toSide === 'UP' ? model.pUp : model.pDown,\r\n      entryFills: timedFills,\r\n    });\r\n    current.orders.push({\r\n      side: toSide,\r\n      source: reason,\r\n      requestedQty: targetQty,\r\n      filledQty,\r\n      maxPrice: maxFillPrice,\r\n      avgPrice: entryCost / filledQty,\r\n      cost: entryCost,\r\n      createdAt: tick.ts,\r\n      probability: toSide === 'UP' ? model.pUp : model.pDown,\r\n      distanceAbs,\r\n      timeRemainingSec,\r\n      fills: timedFills.map((fill) => ({ ...fill })),\r\n    });\r\n\r\n    addLog(\r\n      tick.ts,\r\n      `${reason.toUpperCase()} | ${fromSide}->${toSide} | saiu ${formatQty(soldQty)} @ ${formatPrice(exitPrice)} | entrou ${formatQty(filledQty)} @ ${formatPrice(entryCost / filledQty)} | dist $${distanceAbs.toFixed(2)} | ${Math.round(timeRemainingSec)}s`,\r\n      'stop',\r\n    );\r\n    return true;\r\n  };\r\n\r\n  const maybeProcessPosition = (tick) => {\n    if (!current?.position) return false;\n    const btcPrice = toFiniteNumber(tick.btc_price);\n    const priceToBeat = toFiniteNumber(current.priceToBeat ?? tick.price_to_beat);\n    if (btcPrice == null || priceToBeat == null || !oddsAreValid(tick, params)) return false;\n\r\n    const distanceAbs = Math.abs(btcPrice - priceToBeat);\r\n    const btcAbove = btcPrice >= priceToBeat;\r\n    const timeRemainingSec = secondsRemaining(current, tick);\r\n    const model = estimateProbability(current, tick, params);\r\n    current.lastModel = model;\r\n\r\n    const positionFields = sideFields(tick, current.position.side);\r\n    const currentAsk = positionFields.ask;\r\n    const currentProbability = current.position.side === 'UP' ? model.pUp : model.pDown;\n    const oddDeteriorated = current.entryAsk != null && currentAsk != null && currentAsk <= current.entryAsk * params.deteriorationOddFactor;\n    const probDeteriorated = current.entryProbability != null && currentProbability <= current.entryProbability * params.deteriorationProbFactor;\n    const oppositeActive = (current.position.side === 'UP' && !btcAbove) || (current.position.side === 'DOWN' && btcAbove);\n\n    if (current.inverted) {\n      if (!params.postInversionStopLossEnabled || current.postInversionStopLoss || current.inversionAsk == null) return false;\n      if (currentAsk == null || currentAsk > current.inversionAsk * params.postInversionStopLossFactor) return false;\n\n      const invertedSide = current.position.side;\n      const originalSide = current.originalSide || (invertedSide === 'UP' ? 'DOWN' : 'UP');\n      const invertedQty = current.position.remainingQty;\n      const exitFields = sideFields(tick, invertedSide);\n      const exitPrice = exitFields.bid != null && exitFields.bid > 0 ? exitFields.bid : params.fallbackExitBid;\n      const soldQty = executeSell(tick, invertedQty, exitPrice, 'stoploss_inversao', 'stop');\n      if (soldQty <= 0) return false;\n\n      const originalFields = sideFields(tick, originalSide);\n      if (originalFields.ask == null || originalFields.ask <= 0) return false;\n      const maxFillPrice = Math.min(0.999, originalFields.ask + params.entrySlippageMax);\n      let targetQty = params.postInversionReentryShares > 0\n        ? params.postInversionReentryShares\n        : (current.inversionQty || soldQty) * params.postInversionReentryMultiplier;\n      if (params.positionSizingMode === 'bankroll') {\n        targetQty = Math.max(\n          targetQty,\n          sharesForStake(bankrollStake(params, currentWalletBalance(), params.postInversionReentryStakeMultiplier), maxFillPrice, params.minStake),\n        );\n      }\n\n      const order = executeBuy(tick, originalSide, targetQty, maxFillPrice, 'reforco2', model, distanceAbs, timeRemainingSec);\n      if (!order) return false;\n      current.position = createPosition(originalSide, order.fills.map((fill) => ({ ...fill })));\n      current.orders.push({ ...order, fills: order.fills.map((fill) => ({ ...fill })) });\n      current.postInversionStopLoss = true;\n      addLog(\n        tick.ts,\n        `STOPLOSS INVERSAO | ${invertedSide}->${originalSide} | saiu ${formatQty(soldQty)} @ ${formatPrice(exitPrice)} | entrou ${formatQty(order.filledQty)} @ ${formatPrice(order.avgPrice)} | odd ${currentAsk.toFixed(2)} <= ${(current.inversionAsk * params.postInversionStopLossFactor).toFixed(2)}`,\n        'stop',\n      );\n      return true;\n    }\n\n    if (params.reinforcementEnabled && !current.reinforced && current.entryDistanceToPtb > 0 && distanceAbs >= current.entryDistanceToPtb * params.reinforcementDistanceFactor) {\n      const maxFillPrice = Math.min(params.maxAsk, positionFields.ask + params.entrySlippageMax);\n      let targetQty = params.reinforcementShares;\n      if (targetQty <= 0) {\n        targetQty = params.positionSizingMode === 'bankroll'\n          ? sharesForStake(bankrollStake(params, currentWalletBalance(), params.reinforcementStakeMultiplier), maxFillPrice, params.minStake)\n          : current.position.totalQty;\n      }\n      const order = executeBuy(tick, current.position.side, targetQty, maxFillPrice, 'reforco', model, distanceAbs, timeRemainingSec);\n      if (order) {\n        addToPosition(order);\n        current.reinforced = true;\n        addLog(\n          tick.ts,\n          `REFORCO | ${current.position.side} ${formatQty(order.filledQty)} @ ${formatPrice(order.avgPrice)} | dist $${current.entryDistanceToPtb.toFixed(2)} -> $${distanceAbs.toFixed(2)}`,\n          'entry',\n        );\n        return true;\n      }\n    }\n\n    if (params.deteriorationEnabled && oddDeteriorated && probDeteriorated) {\n      const toSide = current.position.side === 'UP' ? 'DOWN' : 'UP';\n      if (params.deteriorationRequiresCross) {\n        current.deteriorationAlert = true;\n      } else {\n        current.deteriorated = true;\n        if (tryReversePosition(tick, toSide, 'deterioracao', model, distanceAbs, timeRemainingSec)) return true;\n        current.deteriorated = false;\n      }\n    }\n\n    if (params.deteriorationRequiresCross && current.deteriorationAlert && oppositeActive) {\n      const toSide = current.position.side === 'UP' ? 'DOWN' : 'UP';\n      current.deteriorated = true;\n      if (tryReversePosition(tick, toSide, 'deterioracao', model, distanceAbs, timeRemainingSec)) return true;\n      current.deteriorated = false;\n    }\n\n    if (params.inversionEnabled && oppositeActive && distanceAbs >= params.inversionDistanceAbs) {\n      const toSide = current.position.side === 'UP' ? 'DOWN' : 'UP';\n      if (tryReversePosition(tick, toSide, 'inversao', model, distanceAbs, timeRemainingSec)) return true;\n    }\r\n\r\n    return false;\r\n  };\r\n\r\n  const maybeEnter = (tick) => {\r\n    if (!current || current.position) return;\r\n    const timeRemainingSec = secondsRemaining(current, tick);\r\n    if (timeRemainingSec > params.entryWindowStart || timeRemainingSec <= params.entryWindowEnd) return;\r\n    if (eventElapsedSec(current, tick) < params.warmupSec) return;\r\n\r\n    const candidate = scoreCandidate(current, tick, params, currentWalletBalance());\n    if (!candidate) return;\r\n\r\n    const availableQty = availableAskQty(candidate.fields.rawAsks, candidate.maxFill, candidate.fields.ask);\r\n    if (availableQty < candidate.quantity * params.minLiquidityRatio) return;\r\n\r\n    const fills = consumeAsksFromTick(\r\n      candidate.fields.rawAsks,\r\n      candidate.maxFill,\r\n      candidate.quantity,\r\n      current.consumedAsksBySide[candidate.side],\r\n      candidate.fields.ask,\r\n    );\r\n    const filledQty = fills.reduce((sum, fill) => sum + fill.qty, 0);\r\n    const totalCost = fills.reduce((sum, fill) => sum + (fill.qty * fill.price), 0);\r\n    if (filledQty < Math.max(params.minShares, candidate.quantity * params.minLiquidityRatio) || totalCost <= 0) return;\r\n\r\n    const model = current.lastModel || estimateProbability(current, tick, params);\r\n    totalEntries++;\r\n    current.position = createPosition(candidate.side, fills.map((fill) => ({ ...fill, time: tick.ts })));\r\n    current.entryTime = tick.ts;\r\n    current.entryDistanceToPtb = Math.abs(toFiniteNumber(tick.btc_price) - toFiniteNumber(current.priceToBeat ?? tick.price_to_beat));\n    current.entryTimeRemaining = timeRemainingSec;\r\n    current.entryAsk = candidate.ask;\n    current.entryProbability = candidate.probability;\n    current.originalSide = candidate.side;\n    current.entryDiagnostics = {\r\n      probability: candidate.probability,\r\n      edge: candidate.edge,\r\n      ask: candidate.ask,\r\n      bid: candidate.bid,\r\n      spread: candidate.spread,\r\n      distanceToPtb: current.entryDistanceToPtb,\r\n      pUp: model.pUp,\r\n      pDown: model.pDown,\r\n      sigma: model.sigma,\r\n      distanceZ: model.distanceZ,\r\n      momentumZ: model.momentumZ,\r\n      marketLag: model.marketLag,\r\n      fastMove: model.fastMove,\r\n      slowMove: model.slowMove,\r\n    };\r\n    current.orders.push({\r\n      side: candidate.side,\r\n      source: 'entrada',\r\n      requestedQty: candidate.quantity,\r\n      filledQty,\r\n      maxPrice: candidate.maxFill,\r\n      avgPrice: totalCost / filledQty,\r\n      cost: totalCost,\r\n      createdAt: tick.ts,\r\n      probability: candidate.probability,\r\n      edge: candidate.edge,\r\n      distanceAbs: current.entryDistanceToPtb,\r\n      timeRemainingSec,\r\n      fills: fills.map((fill) => ({ ...fill, time: tick.ts })),\r\n    });\r\n\r\n    addLog(\r\n      tick.ts,\r\n      `ENTRADA MOMENTUM | ${candidate.side} ${formatQty(filledQty)} @ ${formatPrice(totalCost / filledQty)} | prob ${(candidate.probability * 100).toFixed(1)}% | edge ${(candidate.edge * 100).toFixed(1)}pp | dist $${current.entryDistanceToPtb.toFixed(2)} | ${Math.round(timeRemainingSec)}s`,\r\n      'entry',\r\n    );\r\n  };\r\n\r\n  const processTick = (tick) => {\r\n    ticksProcessed++;\r\n    if (!periodStart) periodStart = tick.ts;\r\n    periodEnd = tick.ts;\r\n\r\n    const key = eventKey(tick);\r\n    if (!current && completedEvents.has(key)) return;\r\n\r\n    if (!current || tick.condition_id !== current.eventId) {\r\n      if (current) finalizeCurrentEvent('expired', current.eventEnd.toISOString());\r\n      if (completedEvents.has(key)) return;\r\n      startEvent(tick);\r\n    }\r\n\r\n    current.lastTick = tick;\r\n    if (current.priceToBeat == null) current.priceToBeat = toFiniteNumber(tick.price_to_beat);\n\r\n    const tickTime = new Date(tick.ts);\r\n    if (tickTime < new Date(current.eventStart)) return;\r\n\r\n    addSample(current, tick, params);\r\n\r\n    if (tickTime >= current.eventEnd) {\r\n      finalizeCurrentEvent('expired', current.eventEnd.toISOString());\r\n      return;\r\n    }\r\n\r\n    if (maybeProcessPosition(tick)) return;\r\n    maybeEnter(tick);\r\n  };\r\n\r\n  const finish = () => {\r\n    if (current) finalizeCurrentEvent('expired', current.eventEnd.toISOString());\r\n    const enteredEvents = events.filter((item) => item.reason !== 'no_entry');\r\n    const winRate = totalEntries > 0 ? totalWins / totalEntries * 100 : 0;\r\n    const avgPnl = totalEntries > 0 ? totalPnl / totalEntries : 0;\r\n    const maxWin = enteredEvents.length ? Math.max(...enteredEvents.map((item) => item.finalPnl)) : 0;\r\n    const maxLoss = enteredEvents.length ? Math.min(...enteredEvents.map((item) => item.finalPnl)) : 0;\r\n\r\n    let maxDrawdown = 0;\r\n    let peak = 0;\r\n    for (const point of equity) {\r\n      if (point.pnl > peak) peak = point.pnl;\r\n      const drawdown = peak - point.pnl;\r\n      if (drawdown > maxDrawdown) maxDrawdown = drawdown;\r\n    }\r\n\r\n    const advanced = computeAdvancedMetrics(events, params, totalPnl, totalEntries, totalWins, totalLosses);\r\n    return {\r\n      params,\r\n      strategy: params.strategyName,\n      summary: {\r\n        totalEvents,\r\n        totalEntries,\r\n        totalNoEntry,\r\n        totalWins,\r\n        totalLosses,\r\n        winRate: parseFloat(winRate.toFixed(1)),\r\n        totalPnl,\r\n        avgPnl,\r\n        maxWin,\r\n        maxLoss,\r\n        maxDrawdown,\r\n        finalWallet: params.walletSize + totalPnl,\r\n        ...advanced,\r\n      },\r\n      equity,\r\n      events,\r\n      log,\r\n      ticksProcessed,\r\n      periodStart,\r\n      periodEnd,\r\n    };\r\n  };\r\n\r\n  return { processTick, finish };\r\n}\r\n\r\nfunction runMomentumBacktest(rawParams, ticks) {\r\n  const runner = createMomentumBacktestRunner(rawParams);\r\n  for (const tick of ticks) runner.processTick(tick);\r\n  return runner.finish();\r\n}\r\n\r\nasync function runMomentumBacktestInBatches(rawParams, tickBatches) {\n  const runner = createMomentumBacktestRunner(rawParams);\n  for await (const batch of tickBatches) {\n    for (const tick of batch) runner.processTick(tick);\n  }\n  return runner.finish();\n}\n",
  "validation": {
    "ok": true,
    "kind": "runner"
  }
}
